src/__init__.py
src/server.py
mcp_server_ccxt-0.1.0.dist-info/METADATA
mcp_server_ccxt-0.1.0.dist-info/WHEEL
mcp_server_ccxt-0.1.0.dist-info/entry_points.txt
mcp_server_ccxt-0.1.0.dist-info/licenses/LICENSE
mcp_server_ccxt-0.1.0.dist-info/RECORD
