Metadata-Version: 2.4
Name: mcp-server-ccxt
Version: 0.1.0
Summary: Add your description here
License-File: LICENSE
Requires-Python: >=3.10
Requires-Dist: ccxt
Requires-Dist: mcp
